{
  "generated_at": "2026-06-11T12:28:32.485Z",
  "mode": "simulation",
  "bankroll_usd": 924.2899999999998,
  "realized_pnl_today_usd": -19.6,
  "realized_pnl_total_usd": -19.6,
  "open_positions": [
    {
      "ticker": "KXHIGHNY-26JUN12-T90",
      "side": "yes",
      "contracts": 45,
      "price_cents": 41,
      "entry_ts": "2026-06-11T12:28:29.713Z"
    },
    {
      "ticker": "KXHIGHDEN-26JUN11-T76",
      "side": "no",
      "contracts": 34,
      "price_cents": 55,
      "entry_ts": "2026-06-11T08:10:18.245Z"
    },
    {
      "ticker": "KXHIGHCHI-26JUN11-B90.5",
      "side": "no",
      "contracts": 24,
      "price_cents": 79,
      "entry_ts": "2026-06-11T08:10:16.679Z"
    }
  ],
  "recent_decisions": [
    {
      "ts": "2026-06-11T12:28:32.435Z",
      "ticker": "KXHIGHDEN-26JUN11-B78.5",
      "city": "Denver",
      "model_prob": 0.15312275734591652,
      "market_prob": 0.3,
      "edge_pp": 9.687724265408347,
      "side": "no",
      "decision": "reject",
      "gate_failures": "gate0a_extreme_price: limit 100¢ outside [10, 80],gate1_liquidity: counterparty depth 0 < 20,size_zero"
    },
    {
      "ts": "2026-06-11T12:28:32.189Z",
      "ticker": "KXHIGHDEN-26JUN12-B86.5",
      "city": "Denver",
      "model_prob": 0.1749181000259452,
      "market_prob": 0.67,
      "edge_pp": 44.50818999740548,
      "side": "no",
      "decision": "reject",
      "gate_failures": "gate1_liquidity: counterparty depth 1 < 20"
    },
    {
      "ts": "2026-06-11T12:28:32.139Z",
      "ticker": "KXHIGHDEN-26JUN12-B88.5",
      "city": "Denver",
      "model_prob": 0.15163960339762983,
      "market_prob": 0.01,
      "edge_pp": 9.163960339762982,
      "side": "yes",
      "decision": "reject",
      "gate_failures": "gate0a_extreme_price: limit 100¢ outside [10, 80],gate1_liquidity: counterparty depth 0 < 20,size_zero"
    },
    {
      "ts": "2026-06-11T12:28:32.090Z",
      "ticker": "KXHIGHDEN-26JUN12-B90.5",
      "city": "Denver",
      "model_prob": 0.10824326911544813,
      "market_prob": 0.28,
      "edge_pp": 12.175673088455191,
      "side": "no",
      "decision": "reject",
      "gate_failures": "gate0a_extreme_price: limit 99¢ outside [10, 80],gate1_liquidity: counterparty depth 1 < 20,size_zero"
    },
    {
      "ts": "2026-06-11T12:28:32.040Z",
      "ticker": "KXHIGHDEN-26JUN12-T84",
      "city": "Denver",
      "model_prob": 0.7506913317045303,
      "market_prob": 0.6,
      "edge_pp": 10.06913317045303,
      "side": "yes",
      "decision": "reject",
      "gate_failures": "gate1_liquidity: counterparty depth 10 < 20"
    },
    {
      "ts": "2026-06-11T12:28:31.992Z",
      "ticker": "KXHIGHDEN-26JUN12-T91",
      "city": "Denver",
      "model_prob": 0.04879342553966337,
      "market_prob": 0.135,
      "edge_pp": 3.6206574460336647,
      "side": "no",
      "decision": "no_edge",
      "gate_failures": null
    },
    {
      "ts": "2026-06-11T12:28:31.893Z",
      "ticker": "KXHIGHMIA-26JUN11-B87.5",
      "city": "Miami",
      "model_prob": 0.11804638996260519,
      "market_prob": 0.485,
      "edge_pp": 31.695361003739478,
      "side": "no",
      "decision": "reject",
      "gate_failures": "gate1_liquidity: counterparty depth 1 < 20"
    },
    {
      "ts": "2026-06-11T12:28:31.844Z",
      "ticker": "KXHIGHMIA-26JUN11-B89.5",
      "city": "Miami",
      "model_prob": 0.07226410578503595,
      "market_prob": 0.27,
      "edge_pp": 14.773589421496407,
      "side": "no",
      "decision": "reject",
      "gate_failures": "gate0a_extreme_price: limit 99¢ outside [10, 80],gate1_liquidity: counterparty depth 1 < 20,size_zero"
    },
    {
      "ts": "2026-06-11T12:28:31.795Z",
      "ticker": "KXHIGHMIA-26JUN11-B91.5",
      "city": "Miami",
      "model_prob": 0.036423698157188156,
      "market_prob": 0.22,
      "edge_pp": 13.357630184281184,
      "side": "no",
      "decision": "reject",
      "gate_failures": "gate0a_extreme_price: limit 100¢ outside [10, 80],gate1_liquidity: counterparty depth 0 < 20,size_zero"
    },
    {
      "ts": "2026-06-11T12:28:31.746Z",
      "ticker": "KXHIGHMIA-26JUN11-T85",
      "city": "Miami",
      "model_prob": 0.2632889087374999,
      "market_prob": 0.99,
      "edge_pp": 67.67110912625002,
      "side": "no",
      "decision": "reject",
      "gate_failures": "gate0a_extreme_price: limit 100¢ outside [10, 80],gate1_liquidity: counterparty depth 0 < 20,size_zero"
    },
    {
      "ts": "2026-06-11T12:28:31.696Z",
      "ticker": "KXHIGHMIA-26JUN11-T92",
      "city": "Miami",
      "model_prob": 0.02,
      "market_prob": 0.38,
      "edge_pp": 31,
      "side": "no",
      "decision": "reject",
      "gate_failures": "gate0a_extreme_price: limit 100¢ outside [10, 80],gate1_liquidity: counterparty depth 0 < 20,size_zero"
    },
    {
      "ts": "2026-06-11T12:28:31.646Z",
      "ticker": "KXHIGHMIA-26JUN12-B86.5",
      "city": "Miami",
      "model_prob": 0.17367900987922935,
      "market_prob": 0.33,
      "edge_pp": 10.632099012077067,
      "side": "no",
      "decision": "reject",
      "gate_failures": "gate0a_extreme_price: limit 99¢ outside [10, 80],gate1_liquidity: counterparty depth 1 < 20,size_zero"
    },
    {
      "ts": "2026-06-11T12:28:31.597Z",
      "ticker": "KXHIGHMIA-26JUN12-B88.5",
      "city": "Miami",
      "model_prob": 0.14700005853542408,
      "market_prob": 0.01,
      "edge_pp": 8.700005853542407,
      "side": "yes",
      "decision": "reject",
      "gate_failures": "gate0a_extreme_price: limit 100¢ outside [10, 80],gate1_liquidity: counterparty depth 0 < 20,size_zero"
    },
    {
      "ts": "2026-06-11T12:28:31.548Z",
      "ticker": "KXHIGHMIA-26JUN12-B90.5",
      "city": "Miami",
      "model_prob": 0.10244656776072047,
      "market_prob": 0.01,
      "edge_pp": 4.244656776072048,
      "side": "yes",
      "decision": "no_edge",
      "gate_failures": null
    },
    {
      "ts": "2026-06-11T12:28:31.449Z",
      "ticker": "KXHIGHMIA-26JUN12-T86",
      "city": "Miami",
      "model_prob": 0.47121246139565787,
      "market_prob": 0.01,
      "edge_pp": 41.121246139565784,
      "side": "yes",
      "decision": "reject",
      "gate_failures": "gate0a_extreme_price: limit 100¢ outside [10, 80],gate1_liquidity: counterparty depth 0 < 20,size_zero"
    },
    {
      "ts": "2026-06-11T12:28:31.351Z",
      "ticker": "KXHIGHLAX-26JUN11-B72.5",
      "city": "Los Angeles",
      "model_prob": 0.1519421174543073,
      "market_prob": 0.14,
      "edge_pp": -3.805788254569271,
      "side": "yes",
      "decision": "no_edge",
      "gate_failures": null
    },
    {
      "ts": "2026-06-11T12:28:31.302Z",
      "ticker": "KXHIGHLAX-26JUN11-B74.5",
      "city": "Los Angeles",
      "model_prob": 0.10863498307561603,
      "market_prob": 0.435,
      "edge_pp": 27.636501692438394,
      "side": "no",
      "decision": "reject",
      "gate_failures": "gate1_liquidity: counterparty depth 11.33 < 20"
    },
    {
      "ts": "2026-06-11T12:28:31.253Z",
      "ticker": "KXHIGHLAX-26JUN11-B76.5",
      "city": "Los Angeles",
      "model_prob": 0.06395371607835398,
      "market_prob": 0.275,
      "edge_pp": 16.104628392164603,
      "side": "no",
      "decision": "reject",
      "gate_failures": "gate0a_extreme_price: limit 84¢ outside [10, 80],gate1_liquidity: counterparty depth 5.67 < 20"
    },
    {
      "ts": "2026-06-11T12:28:31.203Z",
      "ticker": "KXHIGHLAX-26JUN11-B78.5",
      "city": "Los Angeles",
      "model_prob": 0.03099909478533025,
      "market_prob": 0.49,
      "edge_pp": 40.90009052146697,
      "side": "no",
      "decision": "reject",
      "gate_failures": "gate0a_extreme_price: limit 92¢ outside [10, 80]"
    },
    {
      "ts": "2026-06-11T12:28:31.154Z",
      "ticker": "KXHIGHLAX-26JUN11-T72",
      "city": "Los Angeles",
      "model_prob": 0.23214961584370386,
      "market_prob": 0.29,
      "edge_pp": 0.7850384156296117,
      "side": "no",
      "decision": "no_edge",
      "gate_failures": null
    },
    {
      "ts": "2026-06-11T12:28:31.103Z",
      "ticker": "KXHIGHLAX-26JUN11-T79",
      "city": "Los Angeles",
      "model_prob": 0.02,
      "market_prob": 0.16,
      "edge_pp": 9.000000000000002,
      "side": "no",
      "decision": "reject",
      "gate_failures": "gate0a_extreme_price: limit 84¢ outside [10, 80],gate1_liquidity: counterparty depth 10.41 < 20"
    },
    {
      "ts": "2026-06-11T12:28:30.956Z",
      "ticker": "KXHIGHLAX-26JUN12-B78.5",
      "city": "Los Angeles",
      "model_prob": 0.061702043596359335,
      "market_prob": 0.31,
      "edge_pp": 19.829795640364065,
      "side": "no",
      "decision": "reject",
      "gate_failures": "gate0a_extreme_price: limit 100¢ outside [10, 80],gate1_liquidity: counterparty depth 0 < 20,size_zero"
    },
    {
      "ts": "2026-06-11T12:28:30.907Z",
      "ticker": "KXHIGHLAX-26JUN12-B80.5",
      "city": "Los Angeles",
      "model_prob": 0.029580036341135818,
      "market_prob": 0.01,
      "edge_pp": -3.041996365886418,
      "side": "yes",
      "decision": "no_edge",
      "gate_failures": null
    },
    {
      "ts": "2026-06-11T12:28:30.808Z",
      "ticker": "KXHIGHLAX-26JUN12-T81",
      "city": "Los Angeles",
      "model_prob": 0.02,
      "market_prob": 0.01,
      "edge_pp": -4,
      "side": "yes",
      "decision": "no_edge",
      "gate_failures": null
    },
    {
      "ts": "2026-06-11T12:28:30.758Z",
      "ticker": "KXHIGHCHI-26JUN11-B86.5",
      "city": "Chicago",
      "model_prob": 0.0663170631752037,
      "market_prob": 0.19,
      "edge_pp": 7.3682936824796315,
      "side": "no",
      "decision": "reject",
      "gate_failures": "gate0a_extreme_price: limit 100¢ outside [10, 80],gate1_liquidity: counterparty depth 0 < 20,size_zero"
    },
    {
      "ts": "2026-06-11T12:28:30.709Z",
      "ticker": "KXHIGHCHI-26JUN11-B88.5",
      "city": "Chicago",
      "model_prob": 0.03251165518776011,
      "market_prob": 0.34,
      "edge_pp": 25.74883448122399,
      "side": "no",
      "decision": "reject",
      "gate_failures": "gate0a_extreme_price: limit 100¢ outside [10, 80],gate1_liquidity: counterparty depth 0 < 20,size_zero"
    },
    {
      "ts": "2026-06-11T12:28:30.659Z",
      "ticker": "KXHIGHCHI-26JUN11-B92.5",
      "city": "Chicago",
      "model_prob": 0.02,
      "market_prob": 0.04,
      "edge_pp": -3,
      "side": "no",
      "decision": "no_edge",
      "gate_failures": null
    },
    {
      "ts": "2026-06-11T12:28:30.560Z",
      "ticker": "KXHIGHCHI-26JUN11-T93",
      "city": "Chicago",
      "model_prob": 0.02,
      "market_prob": 0.01,
      "edge_pp": -4,
      "side": "yes",
      "decision": "no_edge",
      "gate_failures": null
    },
    {
      "ts": "2026-06-11T12:28:30.510Z",
      "ticker": "KXHIGHCHI-26JUN12-B77.5",
      "city": "Chicago",
      "model_prob": 0.1541348990468132,
      "market_prob": 0.01,
      "edge_pp": 9.41348990468132,
      "side": "yes",
      "decision": "reject",
      "gate_failures": "gate0a_extreme_price: limit 100¢ outside [10, 80],gate1_liquidity: counterparty depth 0 < 20,size_zero"
    },
    {
      "ts": "2026-06-11T12:28:30.460Z",
      "ticker": "KXHIGHCHI-26JUN12-B79.5",
      "city": "Chicago",
      "model_prob": 0.11153127789644446,
      "market_prob": 0.01,
      "edge_pp": 5.153127789644447,
      "side": "yes",
      "decision": "reject",
      "gate_failures": "gate0a_extreme_price: limit 100¢ outside [10, 80],gate1_liquidity: counterparty depth 0 < 20,size_zero"
    },
    {
      "ts": "2026-06-11T12:28:30.411Z",
      "ticker": "KXHIGHCHI-26JUN12-B81.5",
      "city": "Chicago",
      "model_prob": 0.06645038838317863,
      "market_prob": 0.01,
      "edge_pp": 0.6450388383178627,
      "side": "yes",
      "decision": "no_edge",
      "gate_failures": null
    },
    {
      "ts": "2026-06-11T12:28:30.312Z",
      "ticker": "KXHIGHCHI-26JUN12-T77",
      "city": "Chicago",
      "model_prob": 0.2709308523417209,
      "market_prob": 0.01,
      "edge_pp": 21.093085234172086,
      "side": "yes",
      "decision": "reject",
      "gate_failures": "gate0a_extreme_price: limit 100¢ outside [10, 80],gate1_liquidity: counterparty depth 0 < 20,size_zero"
    },
    {
      "ts": "2026-06-11T12:28:30.213Z",
      "ticker": "KXHIGHNY-26JUN11-B88.5",
      "city": "New York",
      "model_prob": 0.13246773358976371,
      "market_prob": 0.2,
      "edge_pp": 1.7532266410236295,
      "side": "no",
      "decision": "no_edge",
      "gate_failures": null
    },
    {
      "ts": "2026-06-11T12:28:30.163Z",
      "ticker": "KXHIGHNY-26JUN11-B90.5",
      "city": "New York",
      "model_prob": 0.0862579854145028,
      "market_prob": 0.23,
      "edge_pp": 9.37420145854972,
      "side": "no",
      "decision": "reject",
      "gate_failures": "gate0a_extreme_price: limit 84¢ outside [10, 80],gate1_liquidity: counterparty depth 0.41 < 20"
    },
    {
      "ts": "2026-06-11T12:28:30.113Z",
      "ticker": "KXHIGHNY-26JUN11-B92.5",
      "city": "New York",
      "model_prob": 0.04624728275131551,
      "market_prob": 0.28,
      "edge_pp": 18.37527172486845,
      "side": "no",
      "decision": "reject",
      "gate_failures": "gate0a_extreme_price: limit 85¢ outside [10, 80]"
    },
    {
      "ts": "2026-06-11T12:28:30.063Z",
      "ticker": "KXHIGHNY-26JUN11-B94.5",
      "city": "New York",
      "model_prob": 0.020415004804714254,
      "market_prob": 0.21,
      "edge_pp": 13.958499519528573,
      "side": "no",
      "decision": "reject",
      "gate_failures": "gate0a_extreme_price: limit 87¢ outside [10, 80],gate1_liquidity: counterparty depth 2.03 < 20"
    },
    {
      "ts": "2026-06-11T12:28:30.012Z",
      "ticker": "KXHIGHNY-26JUN11-T88",
      "city": "New York",
      "model_prob": 0.11697009533924008,
      "market_prob": 0.49,
      "edge_pp": 32.30299046607599,
      "side": "no",
      "decision": "reject",
      "gate_failures": "gate0a_extreme_price: limit 94¢ outside [10, 80],gate1_liquidity: counterparty depth 10 < 20,size_zero"
    },
    {
      "ts": "2026-06-11T12:28:29.962Z",
      "ticker": "KXHIGHNY-26JUN11-T95",
      "city": "New York",
      "model_prob": 0.02,
      "market_prob": 0.09,
      "edge_pp": 1.9999999999999991,
      "side": "no",
      "decision": "no_edge",
      "gate_failures": null
    },
    {
      "ts": "2026-06-11T12:28:29.912Z",
      "ticker": "KXHIGHNY-26JUN12-B90.5",
      "city": "New York",
      "model_prob": 0.17539453627243862,
      "market_prob": 0.16,
      "edge_pp": -3.4605463727561387,
      "side": "yes",
      "decision": "no_edge",
      "gate_failures": null
    },
    {
      "ts": "2026-06-11T12:28:29.862Z",
      "ticker": "KXHIGHNY-26JUN12-B92.5",
      "city": "New York",
      "model_prob": 0.16434163424219017,
      "market_prob": 0.26,
      "edge_pp": 4.565836575780985,
      "side": "no",
      "decision": "no_edge",
      "gate_failures": null
    },
    {
      "ts": "2026-06-11T12:28:29.813Z",
      "ticker": "KXHIGHNY-26JUN12-B94.5",
      "city": "New York",
      "model_prob": 0.1267922154796739,
      "market_prob": 0.345,
      "edge_pp": 16.820778452032606,
      "side": "no",
      "decision": "reject",
      "gate_failures": "gate0a_extreme_price: limit 84¢ outside [10, 80],gate0b_crossing: already have YES on KXHIGHNY-26JUN12-T90, would cross with NO on KXHIGHNY-26JUN12-B94.5,gate1_liquidity: counterparty depth 10.41 < 20"
    },
    {
      "ts": "2026-06-11T12:28:29.763Z",
      "ticker": "KXHIGHNY-26JUN12-B96.5",
      "city": "New York",
      "model_prob": 0.08054616402937165,
      "market_prob": 0.16,
      "edge_pp": 2.9453835970628353,
      "side": "no",
      "decision": "no_edge",
      "gate_failures": null
    },
    {
      "ts": "2026-06-11T12:28:29.712Z",
      "ticker": "KXHIGHNY-26JUN12-T90",
      "city": "New York",
      "model_prob": 0.6089819011327957,
      "market_prob": 0.29,
      "edge_pp": 26.898190113279572,
      "side": "yes",
      "decision": "trade",
      "gate_failures": null
    },
    {
      "ts": "2026-06-11T12:28:29.662Z",
      "ticker": "KXHIGHNY-26JUN12-T97",
      "city": "New York",
      "model_prob": 0.02,
      "market_prob": 0.165,
      "edge_pp": 9.500000000000002,
      "side": "no",
      "decision": "reject",
      "gate_failures": "gate0a_extreme_price: limit 84¢ outside [10, 80],gate1_liquidity: counterparty depth 9 < 20"
    },
    {
      "ts": "2026-06-11T08:10:18.527Z",
      "ticker": "KXHIGHDEN-26JUN11-B76.5",
      "city": "Denver",
      "model_prob": 0.16152355897458737,
      "market_prob": 0.32,
      "edge_pp": 10.847644102541263,
      "side": "no",
      "decision": "reject",
      "gate_failures": "gate1_liquidity: counterparty depth 1 < 20"
    },
    {
      "ts": "2026-06-11T08:10:18.456Z",
      "ticker": "KXHIGHDEN-26JUN11-B78.5",
      "city": "Denver",
      "model_prob": 0.12220664372312218,
      "market_prob": 0.3,
      "edge_pp": 12.779335627687782,
      "side": "no",
      "decision": "reject",
      "gate_failures": "gate0a_extreme_price: limit 100¢ outside [10, 80],gate1_liquidity: counterparty depth 0 < 20,size_zero"
    },
    {
      "ts": "2026-06-11T08:10:18.244Z",
      "ticker": "KXHIGHDEN-26JUN11-T76",
      "city": "Denver",
      "model_prob": 0.3165530435402981,
      "market_prob": 0.44,
      "edge_pp": 7.344695645970189,
      "side": "no",
      "decision": "trade",
      "gate_failures": null
    },
    {
      "ts": "2026-06-11T08:10:18.033Z",
      "ticker": "KXHIGHMIA-26JUN11-B87.5",
      "city": "Miami",
      "model_prob": 0.14309949950820533,
      "market_prob": 0.325,
      "edge_pp": 13.190050049179469,
      "side": "no",
      "decision": "reject",
      "gate_failures": "gate1_liquidity: counterparty depth 1 < 20"
    },
    {
      "ts": "2026-06-11T08:10:17.962Z",
      "ticker": "KXHIGHMIA-26JUN11-B89.5",
      "city": "Miami",
      "model_prob": 0.09784067416005193,
      "market_prob": 0.225,
      "edge_pp": 7.715932583994807,
      "side": "no",
      "decision": "reject",
      "gate_failures": "gate0a_extreme_price: limit 99¢ outside [10, 80],gate1_liquidity: counterparty depth 1 < 20,size_zero"
    },
    {
      "ts": "2026-06-11T08:10:17.892Z",
      "ticker": "KXHIGHMIA-26JUN11-B91.5",
      "city": "Miami",
      "model_prob": 0.05508108787074861,
      "market_prob": 0.22,
      "edge_pp": 11.49189121292514,
      "side": "no",
      "decision": "reject",
      "gate_failures": "gate0a_extreme_price: limit 100¢ outside [10, 80],gate1_liquidity: counterparty depth 0 < 20,size_zero"
    }
  ],
  "recent_orders": [
    {
      "ts": "2026-06-11T12:28:29.712Z",
      "ticker": "KXHIGHNY-26JUN12-T90",
      "side": "yes",
      "action": "buy",
      "price_cents": 41,
      "count": 45,
      "status": "sim",
      "avg_fill_cents": 41
    },
    {
      "ts": "2026-06-11T08:10:18.244Z",
      "ticker": "KXHIGHDEN-26JUN11-T76",
      "side": "no",
      "action": "buy",
      "price_cents": 55,
      "count": 34,
      "status": "sim",
      "avg_fill_cents": 55
    },
    {
      "ts": "2026-06-11T08:10:16.678Z",
      "ticker": "KXHIGHCHI-26JUN11-B90.5",
      "side": "no",
      "action": "buy",
      "price_cents": 79,
      "count": 24,
      "status": "sim",
      "avg_fill_cents": 79
    },
    {
      "ts": "2026-06-10T20:22:58.441Z",
      "ticker": "KXHIGHMIA-26JUN10-B87.5",
      "side": "no",
      "action": "buy",
      "price_cents": 71,
      "count": 28,
      "status": "sim",
      "avg_fill_cents": 71
    }
  ],
  "pnl_history": [
    {
      "date": "2026-06-11",
      "realized_pnl_usd": -19.6
    }
  ]
}