{
  "generated_at": "2026-05-29T08:39:52.468Z",
  "mode": "simulation",
  "bankroll_usd": 980.2,
  "realized_pnl_today_usd": -19.8,
  "realized_pnl_total_usd": -19.8,
  "open_positions": [
    {
      "ticker": "KXHIGHNY-26MAY29-B78.5",
      "side": "no",
      "contracts": 43,
      "price_cents": 45,
      "entry_ts": "2026-05-29T08:39:50.232Z"
    }
  ],
  "recent_decisions": [
    {
      "ts": "2026-05-29T08:39:52.467Z",
      "ticker": "KXHIGHDEN-26MAY29-B79.5",
      "city": "Denver",
      "model_prob": 0.2604415948452336,
      "market_prob": 0.26,
      "edge_pp": -4.95584051547664,
      "side": "yes",
      "decision": "no_edge",
      "gate_failures": null
    },
    {
      "ts": "2026-05-29T08:39:52.375Z",
      "ticker": "KXHIGHDEN-26MAY29-B81.5",
      "city": "Denver",
      "model_prob": 0.22038215013258733,
      "market_prob": 0.29,
      "edge_pp": 1.9617849867412653,
      "side": "no",
      "decision": "no_edge",
      "gate_failures": null
    },
    {
      "ts": "2026-05-29T08:39:52.282Z",
      "ticker": "KXHIGHDEN-26MAY29-B83.5",
      "city": "Denver",
      "model_prob": 0.12150707775202862,
      "market_prob": 0.22,
      "edge_pp": 4.8492922247971375,
      "side": "no",
      "decision": "no_edge",
      "gate_failures": null
    },
    {
      "ts": "2026-05-29T08:39:52.189Z",
      "ticker": "KXHIGHDEN-26MAY29-B85.5",
      "city": "Denver",
      "model_prob": 0.04363212932693217,
      "market_prob": 0.1,
      "edge_pp": 0.6367870673067841,
      "side": "no",
      "decision": "no_edge",
      "gate_failures": null
    },
    {
      "ts": "2026-05-29T08:39:51.908Z",
      "ticker": "KXHIGHMIA-26MAY29-B84.5",
      "city": "Miami",
      "model_prob": 0.14575845012635713,
      "market_prob": 0.03,
      "edge_pp": 6.575845012635714,
      "side": "yes",
      "decision": "reject",
      "gate_failures": "gate0a_extreme_price: limit 100¢ outside [10, 90],gate1_liquidity: counterparty depth 0 < 50,size_zero"
    },
    {
      "ts": "2026-05-29T08:39:51.815Z",
      "ticker": "KXHIGHMIA-26MAY29-B86.5",
      "city": "Miami",
      "model_prob": 0.23853230803383535,
      "market_prob": 0.11,
      "edge_pp": 7.853230803383536,
      "side": "yes",
      "decision": "reject",
      "gate_failures": "gate0a_extreme_price: limit 100¢ outside [10, 90],gate1_liquidity: counterparty depth 0 < 50,size_zero"
    },
    {
      "ts": "2026-05-29T08:39:51.723Z",
      "ticker": "KXHIGHMIA-26MAY29-B88.5",
      "city": "Miami",
      "model_prob": 0.2543575931393192,
      "market_prob": 0.88,
      "edge_pp": 57.564240686068075,
      "side": "no",
      "decision": "reject",
      "gate_failures": "gate0a_extreme_price: limit 100¢ outside [10, 90],gate1_liquidity: counterparty depth 0 < 50,size_zero"
    },
    {
      "ts": "2026-05-29T08:39:51.537Z",
      "ticker": "KXHIGHMIA-26MAY29-T84",
      "city": "Miami",
      "model_prob": 0.8973626793815974,
      "market_prob": 0.01,
      "edge_pp": 83.73626793815974,
      "side": "yes",
      "decision": "reject",
      "gate_failures": "gate0a_extreme_price: limit 100¢ outside [10, 90],gate1_liquidity: counterparty depth 0 < 50,size_zero"
    },
    {
      "ts": "2026-05-29T08:39:51.444Z",
      "ticker": "KXHIGHMIA-26MAY29-T91",
      "city": "Miami",
      "model_prob": 0.1430612262010269,
      "market_prob": 0.16,
      "edge_pp": -3.30612262010269,
      "side": "no",
      "decision": "no_edge",
      "gate_failures": null
    },
    {
      "ts": "2026-05-29T08:39:51.351Z",
      "ticker": "KXHIGHLAX-26MAY29-B66.5",
      "city": "Los Angeles",
      "model_prob": 0.2151438461763362,
      "market_prob": 0.545,
      "edge_pp": 27.985615382366383,
      "side": "no",
      "decision": "reject",
      "gate_failures": "gate1_liquidity: counterparty depth 45 < 50"
    },
    {
      "ts": "2026-05-29T08:39:51.258Z",
      "ticker": "KXHIGHLAX-26MAY29-B68.5",
      "city": "Los Angeles",
      "model_prob": 0.11115471051968306,
      "market_prob": 0.45,
      "edge_pp": 28.884528948031694,
      "side": "no",
      "decision": "reject",
      "gate_failures": "gate1_liquidity: counterparty depth 39 < 50"
    },
    {
      "ts": "2026-05-29T08:39:51.165Z",
      "ticker": "KXHIGHLAX-26MAY29-B70.5",
      "city": "Los Angeles",
      "model_prob": 0.03673365153350239,
      "market_prob": 0.2,
      "edge_pp": 11.326634846649764,
      "side": "no",
      "decision": "reject",
      "gate_failures": "gate1_liquidity: counterparty depth 40 < 50"
    },
    {
      "ts": "2026-05-29T08:39:50.979Z",
      "ticker": "KXHIGHLAX-26MAY29-T66",
      "city": "Los Angeles",
      "model_prob": 0.30959736847957786,
      "market_prob": 0.065,
      "edge_pp": 19.459736847957785,
      "side": "yes",
      "decision": "reject",
      "gate_failures": "gate1_liquidity: counterparty depth 40 < 50"
    },
    {
      "ts": "2026-05-29T08:39:50.886Z",
      "ticker": "KXHIGHLAX-26MAY29-T73",
      "city": "Los Angeles",
      "model_prob": 0.0019852263709605467,
      "market_prob": 0.5,
      "edge_pp": 44.801477362903945,
      "side": "no",
      "decision": "reject",
      "gate_failures": "gate0a_extreme_price: limit 100¢ outside [10, 90],gate1_liquidity: counterparty depth 0 < 50"
    },
    {
      "ts": "2026-05-29T08:39:50.700Z",
      "ticker": "KXHIGHCHI-26MAY29-B82.5",
      "city": "Chicago",
      "model_prob": 0.1970430137086019,
      "market_prob": 0.45,
      "edge_pp": 20.295698629139814,
      "side": "no",
      "decision": "reject",
      "gate_failures": "gate0a_extreme_price: limit 100¢ outside [10, 90],gate1_liquidity: counterparty depth 0 < 50,size_zero"
    },
    {
      "ts": "2026-05-29T08:39:50.513Z",
      "ticker": "KXHIGHCHI-26MAY29-B86.5",
      "city": "Chicago",
      "model_prob": 0.0313022464417233,
      "market_prob": 0.74,
      "edge_pp": 65.86977535582767,
      "side": "no",
      "decision": "reject",
      "gate_failures": "gate0a_extreme_price: limit 100¢ outside [10, 90],gate1_liquidity: counterparty depth 0 < 50,size_zero"
    },
    {
      "ts": "2026-05-29T08:39:50.420Z",
      "ticker": "KXHIGHCHI-26MAY29-T80",
      "city": "Chicago",
      "model_prob": 0.5274610379481173,
      "market_prob": 0.89,
      "edge_pp": 31.253896205188276,
      "side": "no",
      "decision": "reject",
      "gate_failures": "gate0a_extreme_price: limit 100¢ outside [10, 90],gate1_liquidity: counterparty depth 0 < 50,size_zero"
    },
    {
      "ts": "2026-05-29T08:39:50.325Z",
      "ticker": "KXHIGHCHI-26MAY29-T87",
      "city": "Chicago",
      "model_prob": 0.011773360632317154,
      "market_prob": 0.41,
      "edge_pp": 34.82266393676828,
      "side": "no",
      "decision": "reject",
      "gate_failures": "gate0a_extreme_price: limit 100¢ outside [10, 90],gate1_liquidity: counterparty depth 0 < 50"
    },
    {
      "ts": "2026-05-29T08:39:50.231Z",
      "ticker": "KXHIGHNY-26MAY29-B78.5",
      "city": "New York",
      "model_prob": 0.2515142154443115,
      "market_prob": 0.54,
      "edge_pp": 23.848578455568852,
      "side": "no",
      "decision": "trade",
      "gate_failures": null
    },
    {
      "ts": "2026-05-29T08:39:50.137Z",
      "ticker": "KXHIGHNY-26MAY29-B80.5",
      "city": "New York",
      "model_prob": 0.1697271566252203,
      "market_prob": 0.335,
      "edge_pp": 11.527284337477973,
      "side": "no",
      "decision": "reject",
      "gate_failures": "gate0a_extreme_price: limit 91¢ outside [10, 90],size_zero"
    },
    {
      "ts": "2026-05-29T08:39:50.042Z",
      "ticker": "KXHIGHNY-26MAY29-B82.5",
      "city": "New York",
      "model_prob": 0.07461415516566061,
      "market_prob": 0.17,
      "edge_pp": 4.53858448343394,
      "side": "no",
      "decision": "no_edge",
      "gate_failures": null
    },
    {
      "ts": "2026-05-29T08:39:49.948Z",
      "ticker": "KXHIGHNY-26MAY29-B84.5",
      "city": "New York",
      "model_prob": 0.021356182339156482,
      "market_prob": 0.17,
      "edge_pp": 9.864381766084353,
      "side": "no",
      "decision": "reject",
      "gate_failures": "gate0a_extreme_price: limit 100¢ outside [10, 90],gate1_liquidity: counterparty depth 0 < 50,size_zero"
    },
    {
      "ts": "2026-05-29T08:39:49.856Z",
      "ticker": "KXHIGHNY-26MAY29-T78",
      "city": "New York",
      "model_prob": 0.4553235560529988,
      "market_prob": 0.46,
      "edge_pp": -4.532355605299877,
      "side": "no",
      "decision": "no_edge",
      "gate_failures": null
    },
    {
      "ts": "2026-05-29T08:39:49.762Z",
      "ticker": "KXHIGHNY-26MAY29-T85",
      "city": "New York",
      "model_prob": 0.007231461472858358,
      "market_prob": 0.57,
      "edge_pp": 51.27685385271416,
      "side": "no",
      "decision": "reject",
      "gate_failures": "gate1_liquidity: counterparty depth 10 < 50"
    },
    {
      "ts": "2026-05-24T12:41:24.894Z",
      "ticker": "KXHIGHDEN-26MAY24-B81.5",
      "city": "Denver",
      "model_prob": 0.16356015841591653,
      "market_prob": 0.39,
      "edge_pp": 17.643984158408347,
      "side": "no",
      "decision": "reject",
      "gate_failures": "gate1_liquidity: counterparty depth 0 < 50,size_zero"
    },
    {
      "ts": "2026-05-24T12:41:24.269Z",
      "ticker": "KXHIGHMIA-26MAY24-B89.5",
      "city": "Miami",
      "model_prob": 0.11563449366616563,
      "market_prob": 0.49,
      "edge_pp": 32.43655063338343,
      "side": "no",
      "decision": "reject",
      "gate_failures": "gate1_liquidity: counterparty depth 0 < 50,size_zero"
    },
    {
      "ts": "2026-05-24T12:41:23.738Z",
      "ticker": "KXHIGHLAX-26MAY24-B64.5",
      "city": "Los Angeles",
      "model_prob": 0.06415737962839657,
      "market_prob": 0.08,
      "edge_pp": -3.415737962839657,
      "side": "no",
      "decision": "no_edge",
      "gate_failures": null
    },
    {
      "ts": "2026-05-24T12:41:23.689Z",
      "ticker": "KXHIGHLAX-26MAY24-B66.5",
      "city": "Los Angeles",
      "model_prob": 0.10352591843450265,
      "market_prob": 0.23,
      "edge_pp": 7.647408156549735,
      "side": "no",
      "decision": "reject",
      "gate_failures": "gate1_liquidity: counterparty depth 20 < 50"
    },
    {
      "ts": "2026-05-24T12:41:23.641Z",
      "ticker": "KXHIGHLAX-26MAY24-B68.5",
      "city": "Los Angeles",
      "model_prob": 0.14109340859487712,
      "market_prob": 0.25,
      "edge_pp": 5.8906591405122875,
      "side": "no",
      "decision": "reject",
      "gate_failures": "gate1_liquidity: counterparty depth 0 < 50,size_zero"
    },
    {
      "ts": "2026-05-24T12:41:23.593Z",
      "ticker": "KXHIGHLAX-26MAY24-T62",
      "city": "Los Angeles",
      "model_prob": 0.9710835505100781,
      "market_prob": 0.25,
      "edge_pp": 67.1083550510078,
      "side": "yes",
      "decision": "reject",
      "gate_failures": "gate1_liquidity: counterparty depth 1 < 50"
    },
    {
      "ts": "2026-05-24T12:41:23.544Z",
      "ticker": "KXHIGHLAX-26MAY24-T69",
      "city": "Los Angeles",
      "model_prob": 0.6730578529670261,
      "market_prob": 0.25,
      "edge_pp": 37.30578529670262,
      "side": "yes",
      "decision": "reject",
      "gate_failures": "gate1_liquidity: counterparty depth 0 < 50,size_zero"
    },
    {
      "ts": "2026-05-24T12:41:23.107Z",
      "ticker": "KXHIGHCHI-26MAY24-B76.5",
      "city": "Chicago",
      "model_prob": 0.07142181988726815,
      "market_prob": 0.44,
      "edge_pp": 31.85781801127319,
      "side": "no",
      "decision": "trade",
      "gate_failures": null
    },
    {
      "ts": "2026-05-24T12:41:22.962Z",
      "ticker": "KXHIGHCHI-26MAY24-T79",
      "city": "Chicago",
      "model_prob": 0.16292541185310228,
      "market_prob": 0.25,
      "edge_pp": 3.7074588146897725,
      "side": "no",
      "decision": "no_edge",
      "gate_failures": null
    }
  ],
  "recent_orders": [
    {
      "ts": "2026-05-29T08:39:50.231Z",
      "ticker": "KXHIGHNY-26MAY29-B78.5",
      "side": "no",
      "action": "buy",
      "price_cents": 45,
      "count": 43,
      "status": "sim",
      "avg_fill_cents": 45
    },
    {
      "ts": "2026-05-24T12:41:23.107Z",
      "ticker": "KXHIGHCHI-26MAY24-B76.5",
      "side": "no",
      "action": "buy",
      "price_cents": 55,
      "count": 36,
      "status": "sim",
      "avg_fill_cents": 55
    }
  ],
  "pnl_history": [
    {
      "date": "2026-05-29",
      "realized_pnl_usd": -19.8
    }
  ]
}